Metadata-Version: 2.1
Name: census-data-downloader
Version: 0.0.37
Summary: Download U.S. census data and reformat it for humans
Home-page: http://www.github.com/datadesk/census-data-downloader
Author: Los Angeles Times Data and Graphics Department
Author-email: datadesk@latimes.com
License: MIT
Classifier: Development Status :: 5 - Production/Stable
Classifier: Programming Language :: Python
Classifier: Programming Language :: Python :: 3.6
Classifier: Programming Language :: Python :: 3.7
Classifier: Programming Language :: Python :: 3.8
Classifier: License :: OSI Approved :: MIT License
License-File: LICENSE
Requires-Dist: pandas
Requires-Dist: us
Requires-Dist: census
Requires-Dist: census-data-aggregator
Requires-Dist: click
Requires-Dist: jinja2
